src/__init__.py
src/nlpstreamline.py
nlpstreamline-0.0.10.dist-info/LICENSE.txt
nlpstreamline-0.0.10.dist-info/METADATA
nlpstreamline-0.0.10.dist-info/WHEEL
nlpstreamline-0.0.10.dist-info/top_level.txt
nlpstreamline-0.0.10.dist-info/RECORD
