Metadata-Version: 2.1
Name: nlpstreamline
Version: 0.0.10
Summary: Streamline basic text & NLP processing
Home-page: https://github.com/CielZ001/NLPStreamline
Author: XiZhao
Author-email: cielxxzhao@gmail.com
License: MIT
Classifier: License :: OSI Approved :: MIT License
Classifier: Programming Language :: Python :: 3.8
Classifier: Operating System :: OS Independent
Requires-Python: >=3.8
License-File: LICENSE.txt
Requires-Dist: nltk
Provides-Extra: dev
Requires-Dist: pytest (>=7.0) ; extra == 'dev'
Requires-Dist: twine (>=4.0.2) ; extra == 'dev'
